GRPS/__init__.py
grps-0.0.1.dist-info/METADATA
grps-0.0.1.dist-info/WHEEL
grps-0.0.1.dist-info/licenses/LICENSE
grps-0.0.1.dist-info/RECORD
