Metadata-Version: 2.4
Name: GRPS
Version: 0.0.1
Summary: GRPS
Project-URL: Homepage, https://grps.hydroroll.team
Project-URL: Documentation, https://grps.hydroroll.team
Project-URL: Repository, https://github.com/HydroRoll-Team/GRPS
Project-URL: Changelog, https://grps.hydroroll.team/zh_CN/latest/changelog.html
Author-email: 简律纯 <leader@hydroroll.team>
License: MIT
License-File: LICENSE
Requires-Python: >=3.10
